{"nodes": [{"id": "c_users_matte_bepi_src_bepi_api_v1_requirements_py", "label": "requirements.py", "file_type": "code", "source_file": "bepi/api/v1/requirements.py", "source_location": "L1"}, {"id": "c_users_matte_bepi_src_bepi_api_v1_requirements_list_requirements", "label": "list_requirements()", "file_type": "code", "source_file": "bepi/api/v1/requirements.py", "source_location": "L20", "_callable": true}, {"id": "asyncsession", "label": "AsyncSession", "file_type": "code", "source_file": "", "source_location": "", "origin_file": "C:\\Users\\matte\\BEPI\\src\\bepi\\api\\v1\\requirements.py"}, {"id": "c_users_matte_bepi_src_bepi_api_v1_requirements_create_requirement", "label": "create_requirement()", "file_type": "code", "source_file": "bepi/api/v1/requirements.py", "source_location": "L32", "_callable": true}, {"id": "requirementcreate", "label": "RequirementCreate", "file_type": "code", "source_file": "", "source_location": "", "origin_file": "C:\\Users\\matte\\BEPI\\src\\bepi\\api\\v1\\requirements.py"}, {"id": "c_users_matte_bepi_src_bepi_api_v1_requirements_bulk_import_requirements", "label": "bulk_import_requirements()", "file_type": "code", "source_file": "bepi/api/v1/requirements.py", "source_location": "L41", "_callable": true}, {"id": "c_users_matte_bepi_src_bepi_api_v1_requirements_get_requirement", "label": "get_requirement()", "file_type": "code", "source_file": "bepi/api/v1/requirements.py", "source_location": "L54", "_callable": true}, {"id": "c_users_matte_bepi_src_bepi_api_v1_requirements_update_requirement", "label": "update_requirement()", "file_type": "code", "source_file": "bepi/api/v1/requirements.py", "source_location": "L62", "_callable": true}, {"id": "requirementupdate", "label": "RequirementUpdate", "file_type": "code", "source_file": "", "source_location": "", "origin_file": "C:\\Users\\matte\\BEPI\\src\\bepi\\api\\v1\\requirements.py"}, {"id": "c_users_matte_bepi_src_bepi_api_v1_requirements_delete_requirement", "label": "delete_requirement()", "file_type": "code", "source_file": "bepi/api/v1/requirements.py", "source_location": "L74", "_callable": true}, {"id": "c_users_matte_bepi_src_bepi_api_v1_requirements_get_requirement_trace", "label": "get_requirement_trace()", "file_type": "code", "source_file": "bepi/api/v1/requirements.py", "source_location": "L83", "_callable": true}, {"id": "c_users_matte_bepi_src_bepi_api_v1_requirements_verification_matrix", "label": "verification_matrix()", "file_type": "code", "source_file": "bepi/api/v1/requirements.py", "source_location": "L94", "_callable": true}, {"id": "c_users_matte_bepi_src_bepi_api_v1_requirements_coverage_report", "label": "coverage_report()", "file_type": "code", "source_file": "bepi/api/v1/requirements.py", "source_location": "L135", "_callable": true}], "edges": [{"source": "c_users_matte_bepi_src_bepi_api_v1_requirements_py", "target": "fastapi", "relation": "imports_from", "context": "import", "confidence": "EXTRACTED", "source_file": "bepi/api/v1/requirements.py", "source_location": "L1", "weight": 1.0}, {"source": "c_users_matte_bepi_src_bepi_api_v1_requirements_py", "target": "sqlalchemy", "relation": "imports_from", "context": "import", "confidence": "EXTRACTED", "source_file": "bepi/api/v1/requirements.py", "source_location": "L2", "weight": 1.0}, {"source": "c_users_matte_bepi_src_bepi_api_v1_requirements_py", "target": "sqlalchemy_ext_asyncio", "relation": "imports_from", "context": "import", "confidence": "EXTRACTED", "source_file": "bepi/api/v1/requirements.py", "source_location": "L3", "weight": 1.0}, {"source": "c_users_matte_bepi_src_bepi_api_v1_requirements_py", "target": "bepi_api_v1_deps", "relation": "imports_from", "context": "import", "confidence": "EXTRACTED", "source_file": "bepi/api/v1/requirements.py", "source_location": "L5", "weight": 1.0}, {"source": "c_users_matte_bepi_src_bepi_api_v1_requirements_py", "target": "bepi_core_models_requirement", "relation": "imports_from", "context": "import", "confidence": "EXTRACTED", "source_file": "bepi/api/v1/requirements.py", "source_location": "L6", "weight": 1.0}, {"source": "c_users_matte_bepi_src_bepi_api_v1_requirements_py", "target": "bepi_core_schemas", "relation": "imports_from", "context": "import", "confidence": "EXTRACTED", "source_file": "bepi/api/v1/requirements.py", "source_location": "L7", "weight": 1.0}, {"source": "c_users_matte_bepi_src_bepi_api_v1_requirements_py", "target": "c_users_matte_bepi_src_bepi_api_v1_requirements_list_requirements", "relation": "contains", "confidence": "EXTRACTED", "source_file": "bepi/api/v1/requirements.py", "source_location": "L20", "weight": 1.0}, {"source": "c_users_matte_bepi_src_bepi_api_v1_requirements_list_requirements", "target": "asyncsession", "relation": "references", "context": "parameter_type", "confidence": "EXTRACTED", "source_file": "bepi/api/v1/requirements.py", "source_location": "L20", "weight": 1.0}, {"source": "c_users_matte_bepi_src_bepi_api_v1_requirements_py", "target": "c_users_matte_bepi_src_bepi_api_v1_requirements_create_requirement", "relation": "contains", "confidence": "EXTRACTED", "source_file": "bepi/api/v1/requirements.py", "source_location": "L32", "weight": 1.0}, {"source": "c_users_matte_bepi_src_bepi_api_v1_requirements_create_requirement", "target": "requirementcreate", "relation": "references", "context": "parameter_type", "confidence": "EXTRACTED", "source_file": "bepi/api/v1/requirements.py", "source_location": "L32", "weight": 1.0}, {"source": "c_users_matte_bepi_src_bepi_api_v1_requirements_create_requirement", "target": "asyncsession", "relation": "references", "context": "parameter_type", "confidence": "EXTRACTED", "source_file": "bepi/api/v1/requirements.py", "source_location": "L32", "weight": 1.0}, {"source": "c_users_matte_bepi_src_bepi_api_v1_requirements_py", "target": "c_users_matte_bepi_src_bepi_api_v1_requirements_bulk_import_requirements", "relation": "contains", "confidence": "EXTRACTED", "source_file": "bepi/api/v1/requirements.py", "source_location": "L41", "weight": 1.0}, {"source": "c_users_matte_bepi_src_bepi_api_v1_requirements_bulk_import_requirements", "target": "requirementcreate", "relation": "references", "context": "generic_arg", "confidence": "EXTRACTED", "source_file": "bepi/api/v1/requirements.py", "source_location": "L41", "weight": 1.0}, {"source": "c_users_matte_bepi_src_bepi_api_v1_requirements_bulk_import_requirements", "target": "asyncsession", "relation": "references", "context": "parameter_type", "confidence": "EXTRACTED", "source_file": "bepi/api/v1/requirements.py", "source_location": "L41", "weight": 1.0}, {"source": "c_users_matte_bepi_src_bepi_api_v1_requirements_py", "target": "c_users_matte_bepi_src_bepi_api_v1_requirements_get_requirement", "relation": "contains", "confidence": "EXTRACTED", "source_file": "bepi/api/v1/requirements.py", "source_location": "L54", "weight": 1.0}, {"source": "c_users_matte_bepi_src_bepi_api_v1_requirements_get_requirement", "target": "asyncsession", "relation": "references", "context": "parameter_type", "confidence": "EXTRACTED", "source_file": "bepi/api/v1/requirements.py", "source_location": "L54", "weight": 1.0}, {"source": "c_users_matte_bepi_src_bepi_api_v1_requirements_py", "target": "c_users_matte_bepi_src_bepi_api_v1_requirements_update_requirement", "relation": "contains", "confidence": "EXTRACTED", "source_file": "bepi/api/v1/requirements.py", "source_location": "L62", "weight": 1.0}, {"source": "c_users_matte_bepi_src_bepi_api_v1_requirements_update_requirement", "target": "requirementupdate", "relation": "references", "context": "parameter_type", "confidence": "EXTRACTED", "source_file": "bepi/api/v1/requirements.py", "source_location": "L62", "weight": 1.0}, {"source": "c_users_matte_bepi_src_bepi_api_v1_requirements_update_requirement", "target": "asyncsession", "relation": "references", "context": "parameter_type", "confidence": "EXTRACTED", "source_file": "bepi/api/v1/requirements.py", "source_location": "L62", "weight": 1.0}, {"source": "c_users_matte_bepi_src_bepi_api_v1_requirements_py", "target": "c_users_matte_bepi_src_bepi_api_v1_requirements_delete_requirement", "relation": "contains", "confidence": "EXTRACTED", "source_file": "bepi/api/v1/requirements.py", "source_location": "L74", "weight": 1.0}, {"source": "c_users_matte_bepi_src_bepi_api_v1_requirements_delete_requirement", "target": "asyncsession", "relation": "references", "context": "parameter_type", "confidence": "EXTRACTED", "source_file": "bepi/api/v1/requirements.py", "source_location": "L74", "weight": 1.0}, {"source": "c_users_matte_bepi_src_bepi_api_v1_requirements_py", "target": "c_users_matte_bepi_src_bepi_api_v1_requirements_get_requirement_trace", "relation": "contains", "confidence": "EXTRACTED", "source_file": "bepi/api/v1/requirements.py", "source_location": "L83", "weight": 1.0}, {"source": "c_users_matte_bepi_src_bepi_api_v1_requirements_get_requirement_trace", "target": "asyncsession", "relation": "references", "context": "parameter_type", "confidence": "EXTRACTED", "source_file": "bepi/api/v1/requirements.py", "source_location": "L83", "weight": 1.0}, {"source": "c_users_matte_bepi_src_bepi_api_v1_requirements_py", "target": "c_users_matte_bepi_src_bepi_api_v1_requirements_verification_matrix", "relation": "contains", "confidence": "EXTRACTED", "source_file": "bepi/api/v1/requirements.py", "source_location": "L94", "weight": 1.0}, {"source": "c_users_matte_bepi_src_bepi_api_v1_requirements_verification_matrix", "target": "asyncsession", "relation": "references", "context": "parameter_type", "confidence": "EXTRACTED", "source_file": "bepi/api/v1/requirements.py", "source_location": "L94", "weight": 1.0}, {"source": "c_users_matte_bepi_src_bepi_api_v1_requirements_py", "target": "c_users_matte_bepi_src_bepi_api_v1_requirements_coverage_report", "relation": "contains", "confidence": "EXTRACTED", "source_file": "bepi/api/v1/requirements.py", "source_location": "L135", "weight": 1.0}, {"source": "c_users_matte_bepi_src_bepi_api_v1_requirements_coverage_report", "target": "asyncsession", "relation": "references", "context": "parameter_type", "confidence": "EXTRACTED", "source_file": "bepi/api/v1/requirements.py", "source_location": "L135", "weight": 1.0}], "raw_calls": [{"caller_nid": "c_users_matte_bepi_src_bepi_api_v1_requirements_list_requirements", "callee": "select", "is_member_call": false, "source_file": "bepi/api/v1/requirements.py", "source_location": "L24", "receiver": null}, {"caller_nid": "c_users_matte_bepi_src_bepi_api_v1_requirements_list_requirements", "callee": "Requirement", "is_member_call": false, "indirect": true, "context": "argument", "source_file": "bepi/api/v1/requirements.py", "source_location": "L24"}, {"caller_nid": "c_users_matte_bepi_src_bepi_api_v1_requirements_list_requirements", "callee": "where", "is_member_call": true, "source_file": "bepi/api/v1/requirements.py", "source_location": "L26", "receiver": "q"}, {"caller_nid": "c_users_matte_bepi_src_bepi_api_v1_requirements_list_requirements", "callee": "execute", "is_member_call": true, "source_file": "bepi/api/v1/requirements.py", "source_location": "L27", "receiver": "db"}, {"caller_nid": "c_users_matte_bepi_src_bepi_api_v1_requirements_list_requirements", "callee": "order_by", "is_member_call": true, "source_file": "bepi/api/v1/requirements.py", "source_location": "L27", "receiver": "q"}, {"caller_nid": "c_users_matte_bepi_src_bepi_api_v1_requirements_list_requirements", "callee": "scalars", "is_member_call": true, "source_file": "bepi/api/v1/requirements.py", "source_location": "L28", "receiver": "result"}, {"caller_nid": "c_users_matte_bepi_src_bepi_api_v1_requirements_create_requirement", "callee": "Requirement", "is_member_call": false, "source_file": "bepi/api/v1/requirements.py", "source_location": "L33", "receiver": null}, {"caller_nid": "c_users_matte_bepi_src_bepi_api_v1_requirements_create_requirement", "callee": "model_dump", "is_member_call": true, "source_file": "bepi/api/v1/requirements.py", "source_location": "L33", "receiver": "body"}, {"caller_nid": "c_users_matte_bepi_src_bepi_api_v1_requirements_create_requirement", "callee": "add", "is_member_call": true, "source_file": "bepi/api/v1/requirements.py", "source_location": "L34", "receiver": "db"}, {"caller_nid": "c_users_matte_bepi_src_bepi_api_v1_requirements_create_requirement", "callee": "commit", "is_member_call": true, "source_file": "bepi/api/v1/requirements.py", "source_location": "L35", "receiver": "db"}, {"caller_nid": "c_users_matte_bepi_src_bepi_api_v1_requirements_create_requirement", "callee": "refresh", "is_member_call": true, "source_file": "bepi/api/v1/requirements.py", "source_location": "L36", "receiver": "db"}, {"caller_nid": "c_users_matte_bepi_src_bepi_api_v1_requirements_bulk_import_requirements", "callee": "Requirement", "is_member_call": false, "source_file": "bepi/api/v1/requirements.py", "source_location": "L45", "receiver": null}, {"caller_nid": "c_users_matte_bepi_src_bepi_api_v1_requirements_bulk_import_requirements", "callee": "model_dump", "is_member_call": true, "source_file": "bepi/api/v1/requirements.py", "source_location": "L45", "receiver": "r"}, {"caller_nid": "c_users_matte_bepi_src_bepi_api_v1_requirements_bulk_import_requirements", "callee": "add_all", "is_member_call": true, "source_file": "bepi/api/v1/requirements.py", "source_location": "L46", "receiver": "db"}, {"caller_nid": "c_users_matte_bepi_src_bepi_api_v1_requirements_bulk_import_requirements", "callee": "commit", "is_member_call": true, "source_file": "bepi/api/v1/requirements.py", "source_location": "L47", "receiver": "db"}, {"caller_nid": "c_users_matte_bepi_src_bepi_api_v1_requirements_bulk_import_requirements", "callee": "refresh", "is_member_call": true, "source_file": "bepi/api/v1/requirements.py", "source_location": "L49", "receiver": "db"}, {"caller_nid": "c_users_matte_bepi_src_bepi_api_v1_requirements_get_requirement", "callee": "get", "is_member_call": true, "source_file": "bepi/api/v1/requirements.py", "source_location": "L55", "receiver": "db"}, {"caller_nid": "c_users_matte_bepi_src_bepi_api_v1_requirements_get_requirement", "callee": "Requirement", "is_member_call": false, "indirect": true, "context": "argument", "source_file": "bepi/api/v1/requirements.py", "source_location": "L55"}, {"caller_nid": "c_users_matte_bepi_src_bepi_api_v1_requirements_get_requirement", "callee": "HTTPException", "is_member_call": false, "source_file": "bepi/api/v1/requirements.py", "source_location": "L57", "receiver": null}, {"caller_nid": "c_users_matte_bepi_src_bepi_api_v1_requirements_update_requirement", "callee": "get", "is_member_call": true, "source_file": "bepi/api/v1/requirements.py", "source_location": "L63", "receiver": "db"}, {"caller_nid": "c_users_matte_bepi_src_bepi_api_v1_requirements_update_requirement", "callee": "Requirement", "is_member_call": false, "indirect": true, "context": "argument", "source_file": "bepi/api/v1/requirements.py", "source_location": "L63"}, {"caller_nid": "c_users_matte_bepi_src_bepi_api_v1_requirements_update_requirement", "callee": "HTTPException", "is_member_call": false, "source_file": "bepi/api/v1/requirements.py", "source_location": "L65", "receiver": null}, {"caller_nid": "c_users_matte_bepi_src_bepi_api_v1_requirements_update_requirement", "callee": "items", "is_member_call": true, "source_file": "bepi/api/v1/requirements.py", "source_location": "L66", "receiver": null}, {"caller_nid": "c_users_matte_bepi_src_bepi_api_v1_requirements_update_requirement", "callee": "model_dump", "is_member_call": true, "source_file": "bepi/api/v1/requirements.py", "source_location": "L66", "receiver": "body"}, {"caller_nid": "c_users_matte_bepi_src_bepi_api_v1_requirements_update_requirement", "callee": "commit", "is_member_call": true, "source_file": "bepi/api/v1/requirements.py", "source_location": "L68", "receiver": "db"}, {"caller_nid": "c_users_matte_bepi_src_bepi_api_v1_requirements_update_requirement", "callee": "refresh", "is_member_call": true, "source_file": "bepi/api/v1/requirements.py", "source_location": "L69", "receiver": "db"}, {"caller_nid": "c_users_matte_bepi_src_bepi_api_v1_requirements_delete_requirement", "callee": "get", "is_member_call": true, "source_file": "bepi/api/v1/requirements.py", "source_location": "L75", "receiver": "db"}, {"caller_nid": "c_users_matte_bepi_src_bepi_api_v1_requirements_delete_requirement", "callee": "Requirement", "is_member_call": false, "indirect": true, "context": "argument", "source_file": "bepi/api/v1/requirements.py", "source_location": "L75"}, {"caller_nid": "c_users_matte_bepi_src_bepi_api_v1_requirements_delete_requirement", "callee": "HTTPException", "is_member_call": false, "source_file": "bepi/api/v1/requirements.py", "source_location": "L77", "receiver": null}, {"caller_nid": "c_users_matte_bepi_src_bepi_api_v1_requirements_delete_requirement", "callee": "delete", "is_member_call": true, "source_file": "bepi/api/v1/requirements.py", "source_location": "L78", "receiver": "db"}, {"caller_nid": "c_users_matte_bepi_src_bepi_api_v1_requirements_delete_requirement", "callee": "commit", "is_member_call": true, "source_file": "bepi/api/v1/requirements.py", "source_location": "L79", "receiver": "db"}, {"caller_nid": "c_users_matte_bepi_src_bepi_api_v1_requirements_get_requirement_trace", "callee": "get", "is_member_call": true, "source_file": "bepi/api/v1/requirements.py", "source_location": "L84", "receiver": "db"}, {"caller_nid": "c_users_matte_bepi_src_bepi_api_v1_requirements_get_requirement_trace", "callee": "Requirement", "is_member_call": false, "indirect": true, "context": "argument", "source_file": "bepi/api/v1/requirements.py", "source_location": "L84"}, {"caller_nid": "c_users_matte_bepi_src_bepi_api_v1_requirements_get_requirement_trace", "callee": "HTTPException", "is_member_call": false, "source_file": "bepi/api/v1/requirements.py", "source_location": "L86", "receiver": null}, {"caller_nid": "c_users_matte_bepi_src_bepi_api_v1_requirements_get_requirement_trace", "callee": "execute", "is_member_call": true, "source_file": "bepi/api/v1/requirements.py", "source_location": "L87", "receiver": "db"}, {"caller_nid": "c_users_matte_bepi_src_bepi_api_v1_requirements_get_requirement_trace", "callee": "order_by", "is_member_call": true, "source_file": "bepi/api/v1/requirements.py", "source_location": "L88", "receiver": null}, {"caller_nid": "c_users_matte_bepi_src_bepi_api_v1_requirements_get_requirement_trace", "callee": "where", "is_member_call": true, "source_file": "bepi/api/v1/requirements.py", "source_location": "L88", "receiver": null}, {"caller_nid": "c_users_matte_bepi_src_bepi_api_v1_requirements_get_requirement_trace", "callee": "select", "is_member_call": false, "source_file": "bepi/api/v1/requirements.py", "source_location": "L88", "receiver": null}, {"caller_nid": "c_users_matte_bepi_src_bepi_api_v1_requirements_get_requirement_trace", "callee": "Requirement", "is_member_call": false, "indirect": true, "context": "argument", "source_file": "bepi/api/v1/requirements.py", "source_location": "L88"}, {"caller_nid": "c_users_matte_bepi_src_bepi_api_v1_requirements_get_requirement_trace", "callee": "scalars", "is_member_call": true, "source_file": "bepi/api/v1/requirements.py", "source_location": "L90", "receiver": "result"}, {"caller_nid": "c_users_matte_bepi_src_bepi_api_v1_requirements_verification_matrix", "callee": "execute", "is_member_call": true, "source_file": "bepi/api/v1/requirements.py", "source_location": "L95", "receiver": "db"}, {"caller_nid": "c_users_matte_bepi_src_bepi_api_v1_requirements_verification_matrix", "callee": "order_by", "is_member_call": true, "source_file": "bepi/api/v1/requirements.py", "source_location": "L96", "receiver": null}, {"caller_nid": "c_users_matte_bepi_src_bepi_api_v1_requirements_verification_matrix", "callee": "where", "is_member_call": true, "source_file": "bepi/api/v1/requirements.py", "source_location": "L96", "receiver": null}, {"caller_nid": "c_users_matte_bepi_src_bepi_api_v1_requirements_verification_matrix", "callee": "select", "is_member_call": false, "source_file": "bepi/api/v1/requirements.py", "source_location": "L96", "receiver": null}, {"caller_nid": "c_users_matte_bepi_src_bepi_api_v1_requirements_verification_matrix", "callee": "Requirement", "is_member_call": false, "indirect": true, "context": "argument", "source_file": "bepi/api/v1/requirements.py", "source_location": "L96"}, {"caller_nid": "c_users_matte_bepi_src_bepi_api_v1_requirements_verification_matrix", "callee": "scalars", "is_member_call": true, "source_file": "bepi/api/v1/requirements.py", "source_location": "L98", "receiver": "result"}, {"caller_nid": "c_users_matte_bepi_src_bepi_api_v1_requirements_verification_matrix", "callee": "append", "is_member_call": true, "source_file": "bepi/api/v1/requirements.py", "source_location": "L106", "receiver": "rows"}, {"caller_nid": "c_users_matte_bepi_src_bepi_api_v1_requirements_verification_matrix", "callee": "VerificationMatrixRow", "is_member_call": false, "source_file": "bepi/api/v1/requirements.py", "source_location": "L107", "receiver": null}, {"caller_nid": "c_users_matte_bepi_src_bepi_api_v1_requirements_verification_matrix", "callee": "VerificationMatrixResponse", "is_member_call": false, "source_file": "bepi/api/v1/requirements.py", "source_location": "L124", "receiver": null}, {"caller_nid": "c_users_matte_bepi_src_bepi_api_v1_requirements_coverage_report", "callee": "execute", "is_member_call": true, "source_file": "bepi/api/v1/requirements.py", "source_location": "L136", "receiver": "db"}, {"caller_nid": "c_users_matte_bepi_src_bepi_api_v1_requirements_coverage_report", "callee": "where", "is_member_call": true, "source_file": "bepi/api/v1/requirements.py", "source_location": "L137", "receiver": null}, {"caller_nid": "c_users_matte_bepi_src_bepi_api_v1_requirements_coverage_report", "callee": "select", "is_member_call": false, "source_file": "bepi/api/v1/requirements.py", "source_location": "L137", "receiver": null}, {"caller_nid": "c_users_matte_bepi_src_bepi_api_v1_requirements_coverage_report", "callee": "Requirement", "is_member_call": false, "indirect": true, "context": "argument", "source_file": "bepi/api/v1/requirements.py", "source_location": "L137"}, {"caller_nid": "c_users_matte_bepi_src_bepi_api_v1_requirements_coverage_report", "callee": "scalars", "is_member_call": true, "source_file": "bepi/api/v1/requirements.py", "source_location": "L139", "receiver": "result"}, {"caller_nid": "c_users_matte_bepi_src_bepi_api_v1_requirements_coverage_report", "callee": "get", "is_member_call": true, "source_file": "bepi/api/v1/requirements.py", "source_location": "L152", "receiver": "by_level"}, {"caller_nid": "c_users_matte_bepi_src_bepi_api_v1_requirements_coverage_report", "callee": "get", "is_member_call": true, "source_file": "bepi/api/v1/requirements.py", "source_location": "L153", "receiver": "by_category"}, {"caller_nid": "c_users_matte_bepi_src_bepi_api_v1_requirements_coverage_report", "callee": "get", "is_member_call": true, "source_file": "bepi/api/v1/requirements.py", "source_location": "L154", "receiver": "by_status"}, {"caller_nid": "c_users_matte_bepi_src_bepi_api_v1_requirements_coverage_report", "callee": "CoverageReportResponse", "is_member_call": false, "source_file": "bepi/api/v1/requirements.py", "source_location": "L158", "receiver": null}]}